[
  {
    "name": "bedrijventerrein",
    "type": "ap",
    "title" : "Bedrijventerrein",
    "eap": "OSLO-Bedrijventerrein-impl.eap",
    "diagram": "OSLO-BedrijventerreinImplementatieModel",
    "template": "bedrijventerrein-impl.j2",
    "publication-state": "https://data.vlaanderen.be/id/conceptscheme/StandaardStatus/ErkendeStandaard",
    "publication-date": "2021-04-01",
    "license": "https://data.vlaanderen.be/id/licentie/modellicentie-gratis-hergebruik/v1.0",
    "contributors-file": "stakeholders.csv",
    "contributors-column": "bedrijventerrein",
    "site": "site-skeleton/bedrijventerrein",
    "feedbackurl": "https://github.com/Informatievlaanderen/bron-bedrijventerreinen/issues",
    "standaardregisterurl": "",
    "dependencies": [
        {
          "package": "OSLO-Generiek",
          "packagelabel": "Appplicatieprofiel Generiek-basis",
          "packageurl": "https://data.vlaanderen.be/doc/applicatieprofiel/generiek-basis/"
        }, 
        {
          "package": "OSLO-Perceel",
          "packagelabel": "Appplicatieprofiel bedrijventerrein",
          "packageurl": "https://data.vlaanderen.be/doc/applicatieprofiel/bedrijventerrein"
        },
        {
          "package": "OSLO-Bedrijventerrein",
          "packagelabel": "Appplicatieprofiel bedrijventerrein",
          "packageurl": "https://data.vlaanderen.be/doc/applicatieprofiel/bedrijventerrein"
        } 
    ]
  }
]
